crosscorr/_CCF_1d.cpython-310-darwin.so
crosscorr/_CCF_3d.cpython-310-darwin.so
crosscorr/_CCF_pix.cpython-310-darwin.so
crosscorr/__init__.py
crosscorr/airtovac.py
crosscorr/crosscorr.py
crosscorr/mask.py
crosscorr/utils.py
crosscorr/data/espresso/masks/ESPRESSO_F9.fits
crosscorr/data/espresso/masks/ESPRESSO_G2.fits
crosscorr/data/espresso/masks/ESPRESSO_G8.fits
crosscorr/data/espresso/masks/ESPRESSO_G9.fits
crosscorr/data/espresso/masks/ESPRESSO_K2.fits
crosscorr/data/espresso/masks/ESPRESSO_K6.fits
crosscorr/data/espresso/masks/ESPRESSO_M0.fits
crosscorr/data/espresso/masks/ESPRESSO_M2.fits
crosscorr/data/espresso/masks/ESPRESSO_M3.fits
crosscorr/data/espresso/masks/ESPRESSO_M4.fits
crosscorr/data/espresso/masks/ESPRESSO_M5.fits
crosscorr/data/harps/masks/G2.mas
crosscorr/data/hpf/masks/gj699_combined_stellarframe.mas
crosscorr/data/hpf/masks/specmatch_mask.mas
crosscorr-0.1.2.dist-info/METADATA
crosscorr-0.1.2.dist-info/WHEEL
crosscorr-0.1.2.dist-info/top_level.txt
crosscorr-0.1.2.dist-info/RECORD
