Metadata-Version: 2.1
Name: crosscorr
Version: 0.1.2
Summary: Calculate Binary Cross Correlation Functions
Home-page: https://github.com/gummiks/crosscorr/
Author: Gudmundur Stefansson, Te Han
Author-email: gummiks@gmail.com, tehanhunter@gmail.com
Keywords: Spectra Astronomy
Classifier: License :: OSI Approved :: MIT License
Classifier: Topic :: Scientific/Engineering :: Astronomy
Requires-Dist: numpy ==1.24.3
Requires-Dist: barycorrpy
Requires-Dist: h5py
Requires-Dist: seaborn
